cribl_utilities_cli/__init__.py
cribl_utilities_cli/ingest.py
cribl_utilities_cli/main.py
cribl_utilities_cli/rest_utilities.py
cribl_utilities_cli/schemas.py
cribl_utilities_cli-0.1.7.dist-info/METADATA
cribl_utilities_cli-0.1.7.dist-info/WHEEL
cribl_utilities_cli-0.1.7.dist-info/entry_points.txt
cribl_utilities_cli-0.1.7.dist-info/RECORD
