Metadata-Version: 2.1
Name: cribl-utilities-cli
Version: 0.1.7
Summary: A CLI tool to interact with Cribl
Author: CINQ ICT
Author-email: info@cinqict.nl
Requires-Python: >=3.13,<4.0
Classifier: Programming Language :: Python :: 3
Classifier: Programming Language :: Python :: 3.13
Requires-Dist: pydantic (>=2.10.2,<3.0.0)
Requires-Dist: python-dotenv (>=1.0.1,<2.0.0)
Requires-Dist: requests (>=2.32.3,<3.0.0)
Requires-Dist: tomli (>=2.2.1,<3.0.0)
Requires-Dist: typer (>=0.14.0,<0.15.0)
